[{"place": "Post office", "pincode": "Pincode"}, {"place": "Ainchana", "pincode": "210425"}, {"place": "Ajnar", "pincode": "210423"}, {"place": "Akona", "pincode": "210423"}, {"place": "Aktaunhan", "pincode": "210421"}, {"place": "Ari", "pincode": "210423"}, {"place": "Atrarmaf", "pincode": "210433"}, {"place": "Baghanra", "pincode": "210423"}, {"place": "Bagwaha", "pincode": "210426"}, {"place": "Bahadurpur Kalan", "pincode": "210429"}, {"place": "Bamhauri Kalan", "pincode": "210421"}, {"place": "Bamrara", "pincode": "210421"}, {"place": "Basaut", "pincode": "210425"}, {"place": "Bendo", "pincode": "210429"}, {"place": "Bhandra", "pincode": "210433"}, {"place": "Bharwara", "pincode": "210429"}, {"place": "Bijaypur", "pincode": "210429"}, {"place": "Bila Dakhin", "pincode": "210424"}, {"place": "Bilbai", "pincode": "210427"}, {"place": "Bilkhi", "pincode": "210433"}, {"place": "Budhwara", "pincode": "210423"}, {"place": "Chandauli", "pincode": "210421"}, {"place": "Charkhari State", "pincode": "210421"}, {"place": "Chhani Kalan", "pincode": "210424"}, {"place": "Dharaun", "pincode": "210424"}, {"place": "Dulara", "pincode": "210429"}, {"place": "Gandhi Nagar Mahoba", "pincode": "210427"}, {"place": "Ganj", "pincode": "210424"}, {"place": "Garha", "pincode": "210421"}, {"place": "Gaurahari", "pincode": "210429"}, {"place": "Gyondi", "pincode": "210507"}, {"place": "Jaitpur", "pincode": "210423"}, {"place": "Kabrai", "pincode": "210424"}, {"place": "Kaithi", "pincode": "210429"}, {"place": "Kankuwan", "pincode": "210429"}, {"place": "Karahra Kalan", "pincode": "210427"}, {"place": "Kashipur", "pincode": "210429"}, {"place": "Khajuriha Pahra", "pincode": "210424"}, {"place": "Khanna", "pincode": "210504"}, {"place": "Kharela", "pincode": "210425"}, {"place": "Kilahua", "pincode": "210429"}, {"place": "Kohaniya", "pincode": "210429"}, {"place": "Kulpahar", "pincode": "210426"}, {"place": "Ladpur", "pincode": "210426"}, {"place": "Mahewa", "pincode": "210424"}, {"place": "Maho R.S.", "pincode": "210427"}, {"place": "Mahoba", "pincode": "210427"}, {"place": "Mahua", "pincode": "210429"}, {"place": "Mahuabandh", "pincode": "210423"}, {"place": "Makarbai", "pincode": "210424"}, {"place": "Masoodpura", "pincode": "210429"}, {"place": "Mudhari", "pincode": "210426"}, {"place": "Nagradang", "pincode": "210423"}, {"place": "Nanaura", "pincode": "210433"}, {"place": "Pachara", "pincode": "210423"}, {"place": "Paharia", "pincode": "210429"}, {"place": "Pahra Kalan", "pincode": "210427"}, {"place": "Panwari", "pincode": "210429"}, {"place": "Parsaha", "pincode": "210424"}, {"place": "Paswara", "pincode": "210427"}, {"place": "Patha", "pincode": "210424"}, {"place": "Pawa", "pincode": "210433"}, {"place": "Pewai Sunaicha", "pincode": "210424"}, {"place": "Pewan", "pincode": "210504"}, {"place": "Pipramaf", "pincode": "210433"}, {"place": "Rainpura", "pincode": "210421"}, {"place": "Rewai", "pincode": "210421"}, {"place": "Rewai Sunaicha", "pincode": "210424"}, {"place": "Rewan", "pincode": "210504"}, {"place": "Roori Kalan", "pincode": "210429"}, {"place": "Saidpur", "pincode": "210431"}, {"place": "Salarpur", "pincode": "210433"}, {"place": "Satari", "pincode": "210426"}, {"place": "Sheohar", "pincode": "210424"}, {"place": "Sijahri", "pincode": "210427"}, {"place": "Sijwaha", "pincode": "210433"}, {"place": "Singhaupur Baghari", "pincode": "210424"}, {"place": "Sirsi Kalan", "pincode": "210504"}, {"place": "Sirsi Khurd", "pincode": "210504"}, {"place": "Srinagar", "pincode": "210433"}, {"place": "Sugira", "pincode": "210426"}, {"place": "Supa", "pincode": "210421"}, {"place": "Syondhi", "pincode": "210429"}, {"place": "Teiya", "pincode": "210429"}, {"place": "Tikamau", "pincode": "210427"}, {"place": "Tikaria", "pincode": "210423"}, {"place": "Umari", "pincode": "210429"}]