[{"place": "Post office", "pincode": "Pincode"}, {"place": "Ajgarbahar", "pincode": "495684"}, {"place": "Akalsara", "pincode": "495690"}, {"place": "Amgaon", "pincode": "495690"}, {"place": "Amlidih", "pincode": "495691"}, {"place": "Bade Rabeli", "pincode": "495691"}, {"place": "Bade Seepat", "pincode": "495691"}, {"place": "Bagrad", "pincode": "495118"}, {"place": "Baksahi", "pincode": "495449"}, {"place": "Balgi Project Korba", "pincode": "495455"}, {"place": "Bango Dam", "pincode": "495448"}, {"place": "Banjhiban", "pincode": "495445"}, {"place": "Banki Mongra", "pincode": "495447"}, {"place": "Bansital", "pincode": "495118"}, {"place": "Barpali (J)", "pincode": "495674"}, {"place": "Barpali (S)", "pincode": "495674"}, {"place": "Batra", "pincode": "495449"}, {"place": "Beharchuwa", "pincode": "495674"}, {"place": "Beladula", "pincode": "495690"}, {"place": "Beljhiria", "pincode": "495118"}, {"place": "Beltara", "pincode": "495449"}, {"place": "Bhairotal", "pincode": "495454"}, {"place": "Bhaisma", "pincode": "495674"}, {"place": "Bharridand", "pincode": "495118"}, {"place": "Bhilaibazar", "pincode": "495454"}, {"place": "Bhothia", "pincode": "495690"}, {"place": "Binjhra", "pincode": "495445"}, {"place": "Birda", "pincode": "495446"}, {"place": "Boida", "pincode": "495446"}, {"place": "Bundeli", "pincode": "495683"}, {"place": "Chachia", "pincode": "495674"}, {"place": "Chadhedi", "pincode": "495118"}, {"place": "Chainpur", "pincode": "495446"}, {"place": "Chaitma", "pincode": "495449"}, {"place": "Champa", "pincode": "495674"}, {"place": "Charpara", "pincode": "495691"}, {"place": "Chhapora", "pincode": "495691"}, {"place": "Chhuri", "pincode": "495450"}, {"place": "Chiknipali", "pincode": "495674"}, {"place": "Chirra", "pincode": "495674"}, {"place": "Chorbhatti", "pincode": "495674"}, {"place": "Choria", "pincode": "495686"}, {"place": "Dadarkala", "pincode": "495674"}, {"place": "Dadarkhurd", "pincode": "495682"}, {"place": "Darrabhatha", "pincode": "495445"}, {"place": "Deepika Project Korba", "pincode": "495452"}, {"place": "Dhelwadih", "pincode": "495445"}, {"place": "Durpa", "pincode": "495454"}, {"place": "Garh Uproda", "pincode": "495684"}, {"place": "Gatwa", "pincode": "495446"}, {"place": "Gerwa", "pincode": "495450"}, {"place": "Gevra Basti", "pincode": "495454"}, {"place": "Ghinara", "pincode": "495674"}, {"place": "Ghiwra", "pincode": "495661"}, {"place": "Gidhkunwari", "pincode": "495674"}, {"place": "Godhi", "pincode": "495683"}, {"place": "Gopalpur", "pincode": "495450"}, {"place": "Gursia", "pincode": "495448"}, {"place": "Hardi Bazar", "pincode": "495446"}, {"place": "Harethikala", "pincode": "495661"}, {"place": "Hasdeo Project Korba", "pincode": "495677"}, {"place": "Hasod", "pincode": "495661"}, {"place": "Jali", "pincode": "495449"}, {"place": "Jalke", "pincode": "495448"}, {"place": "Jamnipali", "pincode": "495450"}, {"place": "Jarwe", "pincode": "495674"}, {"place": "Jatga", "pincode": "495445"}, {"place": "Jawali", "pincode": "495445"}, {"place": "Jevra", "pincode": "495446"}, {"place": "Jhalraundha", "pincode": "495690"}, {"place": "Jilga", "pincode": "495674"}, {"place": "Kachanda", "pincode": "495690"}, {"place": "Kaitha", "pincode": "495661"}, {"place": "Kamrid", "pincode": "495660"}, {"place": "Kanki", "pincode": "495446"}, {"place": "Kapisda", "pincode": "495660"}, {"place": "Kapot", "pincode": "495449"}, {"place": "Karhani", "pincode": "495118"}, {"place": "Karnaud", "pincode": "495660"}, {"place": "Kartalachak", "pincode": "495674"}, {"place": "Kashigarh", "pincode": "495690"}, {"place": "Katetara", "pincode": "495690"}, {"place": "Katghora", "pincode": "495445"}, {"place": "Khajurani", "pincode": "495690"}, {"place": "Khamharia", "pincode": "495446"}, {"place": "Khemda", "pincode": "495691"}, {"place": "Kikirda", "pincode": "495661"}, {"place": "Korba Colliery", "pincode": "495677"}, {"place": "Korba", "pincode": "495677"}, {"place": "Korba Town", "pincode": "495677"}, {"place": "Korbi", "pincode": "495448"}, {"place": "Korbi", "pincode": "495446"}, {"place": "Korkoma", "pincode": "495683"}, {"place": "Kotmer", "pincode": "495674"}, {"place": "Kudmura", "pincode": "495674"}, {"place": "Kudurmal", "pincode": "495674"}, {"place": "Kurda", "pincode": "495691"}, {"place": "Kusmunda Colliery", "pincode": "495454"}, {"place": "Lafa", "pincode": "495449"}, {"place": "Lakhali", "pincode": "495660"}, {"place": "Madai", "pincode": "495448"}, {"place": "Madanpur", "pincode": "495448"}, {"place": "Malda", "pincode": "495661"}, {"place": "Manikpur Colliery", "pincode": "495682"}, {"place": "Marghatti", "pincode": "495691"}, {"place": "Mongra", "pincode": "495447"}, {"place": "Morga", "pincode": "495448"}, {"place": "Mudhali", "pincode": "495446"}, {"place": "Mukta", "pincode": "495691"}, {"place": "Murli", "pincode": "495446"}, {"place": "Nariyara", "pincode": "495691"}, {"place": "Nawapara", "pincode": "495691"}, {"place": "Nonbirra", "pincode": "495449"}, {"place": "Nonbirra", "pincode": "495674"}, {"place": "Nunera", "pincode": "495449"}, {"place": "Odekera", "pincode": "495690"}, {"place": "Pachra", "pincode": "495448"}, {"place": "Pali", "pincode": "495448"}, {"place": "Pali", "pincode": "495449"}, {"place": "Pandania", "pincode": "495454"}, {"place": "Pantora", "pincode": "495446"}, {"place": "Parasi", "pincode": "495118"}, {"place": "Parsada", "pincode": "495661"}, {"place": "Pasarkhet", "pincode": "495683"}, {"place": "Patpara", "pincode": "495449"}, {"place": "Pendri", "pincode": "495661"}, {"place": "Pidia", "pincode": "495674"}, {"place": "Pihrid", "pincode": "495691"}, {"place": "Pirda", "pincode": "495691"}, {"place": "Pondi-Uproda", "pincode": "495448"}, {"place": "Pondilafa", "pincode": "495449"}, {"place": "Pondishankar", "pincode": "495660"}, {"place": "Pragati Nagar", "pincode": "495450"}, {"place": "Rajgamar Colliery", "pincode": "495683"}, {"place": "Rajkamma", "pincode": "495445"}, {"place": "Rampur", "pincode": "495674"}, {"place": "Ranjana", "pincode": "495449"}, {"place": "Rewa", "pincode": "495445"}, {"place": "Risdi", "pincode": "495683"}, {"place": "Rohda", "pincode": "495660"}, {"place": "Rumga", "pincode": "495118"}, {"place": "Salni", "pincode": "495690"}, {"place": "Saragbundia", "pincode": "495674"}, {"place": "Sarwani", "pincode": "495660"}, {"place": "Semardarri", "pincode": "495118"}, {"place": "Semaria", "pincode": "495661"}, {"place": "Sendri", "pincode": "495690"}, {"place": "Sendripali", "pincode": "495674"}, {"place": "Seoni", "pincode": "495118"}, {"place": "Shish", "pincode": "495449"}, {"place": "Siladehi", "pincode": "495661"}, {"place": "Singhra", "pincode": "495691"}, {"place": "Sirmina", "pincode": "495448"}, {"place": "Solwan", "pincode": "495674"}, {"place": "Sonthi", "pincode": "495660"}, {"place": "Sutarra", "pincode": "495445"}, {"place": "Syang", "pincode": "495674"}, {"place": "Taldeori", "pincode": "495661"}, {"place": "Tanakhar", "pincode": "495445"}, {"place": "Tarod", "pincode": "495446"}, {"place": "Thathari", "pincode": "495690"}, {"place": "Tilkeja", "pincode": "495674"}, {"place": "Tiwarta", "pincode": "495449"}, {"place": "Tuman", "pincode": "495445"}, {"place": "Tuman", "pincode": "495674"}, {"place": "Tusar", "pincode": "495690"}, {"place": "Usad", "pincode": "495118"}, {"place": "Utarda", "pincode": "495446"}, {"place": "Vidyut Nagar Korba", "pincode": "495450"}, {"place": "Vikas Bhawan", "pincode": "495450"}, {"place": "Wcl Gevra Project", "pincode": "495452"}]