[{"place": "Post office", "pincode": "Pincode"}, {"place": "Adamdour", "pincode": "814160"}, {"place": "Agiyamore", "pincode": "814153"}, {"place": "Amlo", "pincode": "814133"}, {"place": "Amour", "pincode": "814160"}, {"place": "Anjana", "pincode": "814154"}, {"place": "Asarimadhuri", "pincode": "814153"}, {"place": "Azampakariya", "pincode": "814155"}, {"place": "Baghmara", "pincode": "814153"}, {"place": "Bahdurchak", "pincode": "813208"}, {"place": "Bajitpur", "pincode": "814160"}, {"place": "Baksara", "pincode": "814133"}, {"place": "Bandanbar", "pincode": "814147"}, {"place": "Banerchua", "pincode": "814165"}, {"place": "Bans Jori", "pincode": "814156"}, {"place": "Bara Banghi", "pincode": "814153"}, {"place": "Barasimra", "pincode": "814165"}, {"place": "Barmasiya", "pincode": "814147"}, {"place": "Basantpur", "pincode": "814133"}, {"place": "Basantrai", "pincode": "814155"}, {"place": "Belbadda", "pincode": "814160"}, {"place": "Beniadih", "pincode": "813208"}, {"place": "Bhadharia", "pincode": "814147"}, {"place": "Bhagmara", "pincode": "813208"}, {"place": "Bhagya", "pincode": "813208"}, {"place": "Bhanjpur", "pincode": "814154"}, {"place": "Bharta Chak", "pincode": "814154"}, {"place": "Bisambharchak", "pincode": "814155"}, {"place": "Biswaskhani", "pincode": "814155"}, {"place": "Boarijore", "pincode": "813208"}, {"place": "Burhi Kura", "pincode": "814153"}, {"place": "Chandanahat", "pincode": "814156"}, {"place": "Chapri", "pincode": "813208"}, {"place": "Chapri", "pincode": "814133"}, {"place": "Chatra", "pincode": "814153"}, {"place": "China Dhab", "pincode": "814156"}, {"place": "Dama", "pincode": "814153"}, {"place": "Damruhat", "pincode": "814153"}, {"place": "Danrey Katchery", "pincode": "814153"}, {"place": "Dariapur", "pincode": "814160"}, {"place": "Debjore", "pincode": "815355"}, {"place": "Deobandha", "pincode": "814133"}, {"place": "Deodawr", "pincode": "814153"}, {"place": "Dewanchak", "pincode": "814160"}, {"place": "Dhamni", "pincode": "816102"}, {"place": "Dharmodih", "pincode": "814154"}, {"place": "Dighi", "pincode": "814154"}, {"place": "Dighisiwanpur", "pincode": "814160"}, {"place": "Doi", "pincode": "814160"}, {"place": "Dubrajpur", "pincode": "814133"}, {"place": "Fasia", "pincode": "814133"}, {"place": "Gajanda", "pincode": "814165"}, {"place": "Gandhigram", "pincode": "814133"}, {"place": "Gangtaklan", "pincode": "814133"}, {"place": "Ghanghrabandh", "pincode": "814153"}, {"place": "Ghat Kuruwa", "pincode": "814147"}, {"place": "Ghatdumariya", "pincode": "814133"}, {"place": "Ghatiyari", "pincode": "814156"}, {"place": "Ghatkusmani", "pincode": "814133"}, {"place": "Ghoothi", "pincode": "814154"}, {"place": "Godda College", "pincode": "814133"}, {"place": "Godda", "pincode": "814133"}, {"place": "Gorhia", "pincode": "814165"}, {"place": "Gorikitta", "pincode": "814160"}, {"place": "Gumma", "pincode": "814133"}, {"place": "Hanwara", "pincode": "814154"}, {"place": "Haripur Gorbana", "pincode": "814133"}, {"place": "Hariyari", "pincode": "814153"}, {"place": "Hilaway", "pincode": "814133"}, {"place": "Jaminipaharpur", "pincode": "814133"}, {"place": "K. Parsa", "pincode": "814155"}, {"place": "Kadma", "pincode": "814155"}, {"place": "Kairadih", "pincode": "814153"}, {"place": "Kairasol", "pincode": "814102"}, {"place": "Kaitha", "pincode": "814155"}, {"place": "Kamaldouri", "pincode": "814165"}, {"place": "Kasba", "pincode": "814154"}, {"place": "Kasbadudhanichak", "pincode": "814160"}, {"place": "Kathaun", "pincode": "814153"}, {"place": "Kero Bazar", "pincode": "814147"}, {"place": "Kerwarbelsar", "pincode": "814147"}, {"place": "Khariani", "pincode": "814147"}, {"place": "Khatnai", "pincode": "814133"}, {"place": "Koila", "pincode": "814154"}, {"place": "Korkaghat", "pincode": "814133"}, {"place": "Kouribahiar", "pincode": "814133"}, {"place": "Kurmichak", "pincode": "814156"}, {"place": "Kushmara", "pincode": "814154"}, {"place": "Kushmil", "pincode": "814154"}, {"place": "Kusumghati", "pincode": "814147"}, {"place": "Lahati", "pincode": "814147"}, {"place": "Lakarmara", "pincode": "814160"}, {"place": "Lalmatia Colliery", "pincode": "814165"}, {"place": "Latauna", "pincode": "814133"}, {"place": "Latta", "pincode": "814153"}, {"place": "Laxmipur Bhojichak", "pincode": "814155"}, {"place": "Logain", "pincode": "814154"}, {"place": "Lohandia Bazar", "pincode": "814165"}, {"place": "Lohbandha", "pincode": "814133"}, {"place": "Lukluki", "pincode": "814133"}, {"place": "M. Chikaniya", "pincode": "814151"}, {"place": "Madhurai", "pincode": "814165"}, {"place": "Maheshtikri", "pincode": "814155"}, {"place": "Mahgama", "pincode": "814154"}, {"place": "Makhni", "pincode": "814133"}, {"place": "Mal Bhandaridih", "pincode": "814154"}, {"place": "Malini", "pincode": "814133"}, {"place": "Malrampur", "pincode": "814133"}, {"place": "Maniarkajral", "pincode": "813208"}, {"place": "Marpa", "pincode": "814160"}, {"place": "Meharma", "pincode": "814160"}, {"place": "Mohani", "pincode": "814153"}, {"place": "Mohanpur", "pincode": "814154"}, {"place": "Mohanpur", "pincode": "814133"}, {"place": "Mokalchak", "pincode": "814155"}, {"place": "Mordiha", "pincode": "813208"}, {"place": "Motia", "pincode": "814133"}, {"place": "Motiya Dumariya", "pincode": "814133"}, {"place": "Naraini", "pincode": "814154"}, {"place": "Nawdiha", "pincode": "814153"}, {"place": "Naya Nagar", "pincode": "814154"}, {"place": "Nepura", "pincode": "814133"}, {"place": "Nunajore", "pincode": "814154"}, {"place": "Nunbatta", "pincode": "814156"}, {"place": "P. Barmasiya", "pincode": "814153"}, {"place": "Padampur", "pincode": "814153"}, {"place": "Paharpur", "pincode": "814156"}, {"place": "Parariya", "pincode": "814155"}, {"place": "Parspani", "pincode": "814147"}, {"place": "Parua", "pincode": "814155"}, {"place": "Pasai", "pincode": "814153"}, {"place": "Pathergama", "pincode": "814147"}, {"place": "Pathra", "pincode": "814133"}, {"place": "Pindra Hat", "pincode": "814153"}, {"place": "Pipra", "pincode": "814147"}, {"place": "Pratappur", "pincode": "814160"}, {"place": "Raghunathpur Lathibari", "pincode": "814153"}, {"place": "Raja Bhitaa", "pincode": "814147"}, {"place": "Ramla Dikwani", "pincode": "814133"}, {"place": "Rangachak", "pincode": "813208"}, {"place": "Rupni", "pincode": "814155"}, {"place": "Sahapur Beldiha", "pincode": "814155"}, {"place": "Saidapur", "pincode": "814133"}, {"place": "Salaiya", "pincode": "814153"}, {"place": "Samri", "pincode": "814155"}, {"place": "Sanour", "pincode": "814155"}, {"place": "Sarba", "pincode": "814133"}, {"place": "Sarbhanga", "pincode": "814165"}, {"place": "Sarouni Bazar", "pincode": "814156"}, {"place": "Simarda", "pincode": "814133"}, {"place": "Simlongcolliery", "pincode": "816102"}, {"place": "Sunder Pahari", "pincode": "814156"}, {"place": "Sundmara", "pincode": "814156"}, {"place": "Surni", "pincode": "814160"}, {"place": "Tardiha", "pincode": "814147"}, {"place": "Thakurgangti", "pincode": "813208"}, {"place": "Tularambhuska", "pincode": "814160"}]