[{"place": "Post office", "pincode": "Pincode"}, {"place": "Achladi", "pincode": "576225"}, {"place": "Adi-udupi", "pincode": "576101"}, {"place": "Admar", "pincode": "574119"}, {"place": "Airody", "pincode": "576226"}, {"place": "Ajekar", "pincode": "574101"}, {"place": "Ajrihara", "pincode": "576283"}, {"place": "Alevoor", "pincode": "574118"}, {"place": "Alur", "pincode": "576233"}, {"place": "Amasebail", "pincode": "576227"}, {"place": "Ambalapadi", "pincode": "576103"}, {"place": "Ampar", "pincode": "576211"}, {"place": "Anagalli", "pincode": "576211"}, {"place": "Andar", "pincode": "574101"}, {"place": "Ardi", "pincode": "576212"}, {"place": "Arekandige", "pincode": "576124"}, {"place": "Aroor", "pincode": "576213"}, {"place": "Asodu", "pincode": "576222"}, {"place": "Athradi", "pincode": "576107"}, {"place": "Attur", "pincode": "576117"}, {"place": "Avarse", "pincode": "576223"}, {"place": "Avral", "pincode": "574103"}, {"place": "Bada", "pincode": "574117"}, {"place": "Badagabettu", "pincode": "576107"}, {"place": "Badakere", "pincode": "576224"}, {"place": "Badanidiyur", "pincode": "576115"}, {"place": "Baidabettu", "pincode": "576234"}, {"place": "Baikadi", "pincode": "576213"}, {"place": "Bailur", "pincode": "574102"}, {"place": "Bajegoli", "pincode": "574122"}, {"place": "Balkur", "pincode": "576211"}, {"place": "Bannadi", "pincode": "576225"}, {"place": "Bannanje", "pincode": "576101"}, {"place": "Barkur", "pincode": "576210"}, {"place": "Barkur Town", "pincode": "576210"}, {"place": "Basrur", "pincode": "576211"}, {"place": "Beejadi", "pincode": "576222"}, {"place": "Belady", "pincode": "574129"}, {"place": "Belanje", "pincode": "576112"}, {"place": "Belapu", "pincode": "574117"}, {"place": "Bellampalli", "pincode": "576124"}, {"place": "Bellarpadi", "pincode": "576113"}, {"place": "Belmannu", "pincode": "576111"}, {"place": "Belur Devasthanabettu", "pincode": "576221"}, {"place": "Belve", "pincode": "576212"}, {"place": "Bennekudru", "pincode": "576210"}, {"place": "Bhairanje", "pincode": "576107"}, {"place": "Bhantakal", "pincode": "574115"}, {"place": "Bijur", "pincode": "576232"}, {"place": "Bola", "pincode": "574110"}, {"place": "Bolakodi", "pincode": "576121"}, {"place": "Borkatte", "pincode": "574107"}, {"place": "Brahmavara", "pincode": "576213"}, {"place": "Byndoor", "pincode": "576214"}, {"place": "Chanthar", "pincode": "576213"}, {"place": "Chara", "pincode": "576112"}, {"place": "Cherkadi", "pincode": "576215"}, {"place": "Chitpadi", "pincode": "576101"}, {"place": "Chittoor", "pincode": "576233"}, {"place": "Devalkunda", "pincode": "576230"}, {"place": "Dist. Offices Complex Manipal", "pincode": "576104"}, {"place": "Doddanagudde", "pincode": "576102"}, {"place": "Doopadakatte", "pincode": "574110"}, {"place": "Durga", "pincode": "576117"}, {"place": "Ellare", "pincode": "574108"}, {"place": "Gandhi-maidan", "pincode": "576201"}, {"place": "Ganguli", "pincode": "576216"}, {"place": "Golihole", "pincode": "576214"}, {"place": "Guddeangadi", "pincode": "576113"}, {"place": "Gujjadi", "pincode": "576247"}, {"place": "Gulvadi", "pincode": "576283"}, {"place": "Gummahola", "pincode": "576212"}, {"place": "Gundyadka", "pincode": "574102"}, {"place": "Hadavu", "pincode": "576235"}, {"place": "Hadiangady", "pincode": "574101"}, {"place": "Hakladi", "pincode": "576235"}, {"place": "Haladi-28", "pincode": "576222"}, {"place": "Haladi-76", "pincode": "576222"}, {"place": "Halasinakatte", "pincode": "574113"}, {"place": "Halladi-harkadi", "pincode": "576210"}, {"place": "Hallihole", "pincode": "576229"}, {"place": "Halnadu", "pincode": "576211"}, {"place": "Haluvalli", "pincode": "576215"}, {"place": "Hanehalli", "pincode": "576210"}, {"place": "Hanglur", "pincode": "576217"}, {"place": "Haradi", "pincode": "576213"}, {"place": "Hardalli-mandalli", "pincode": "576222"}, {"place": "Harkur", "pincode": "576233"}, {"place": "Hattiangadi", "pincode": "576283"}, {"place": "Havanje", "pincode": "576124"}, {"place": "Hebri", "pincode": "576112"}, {"place": "Hejmadi", "pincode": "574103"}, {"place": "Hejmadikodi", "pincode": "574103"}, {"place": "Hemmadi", "pincode": "576230"}, {"place": "Hengavalli", "pincode": "576212"}, {"place": "Heranjal", "pincode": "576219"}, {"place": "Herga", "pincode": "576107"}, {"place": "Herikudru", "pincode": "576230"}, {"place": "Hermunde", "pincode": "574101"}, {"place": "Herur", "pincode": "576213"}, {"place": "Herur-92", "pincode": "574115"}, {"place": "Heskethur", "pincode": "576210"}, {"place": "Hiliyana", "pincode": "576212"}, {"place": "Hirebettu", "pincode": "576107"}, {"place": "Hirgana", "pincode": "576117"}, {"place": "Hiriadka", "pincode": "576113"}, {"place": "Hiriangady", "pincode": "574104"}, {"place": "Hoode", "pincode": "576115"}, {"place": "Hosadu", "pincode": "576247"}, {"place": "Hosala", "pincode": "576210"}, {"place": "Hosangadi", "pincode": "576282"}, {"place": "Hosmar", "pincode": "574107"}, {"place": "Hungarcutta", "pincode": "576218"}, {"place": "Hunsemakki", "pincode": "576222"}, {"place": "Idu", "pincode": "574109"}, {"place": "Idurkunhady", "pincode": "576233"}, {"place": "Inna", "pincode": "576121"}, {"place": "Innanje", "pincode": "576122"}, {"place": "Iruvail", "pincode": "574144"}, {"place": "Irvathur", "pincode": "574114"}, {"place": "Jadkal", "pincode": "576233"}, {"place": "Jansale", "pincode": "576229"}, {"place": "Janvarkatte", "pincode": "576223"}, {"place": "Japthi", "pincode": "576211"}, {"place": "Jarkala", "pincode": "574101"}, {"place": "Kabbinale", "pincode": "576112"}, {"place": "Kadekar", "pincode": "576103"}, {"place": "Kadthala", "pincode": "574108"}, {"place": "Kadur", "pincode": "576234"}, {"place": "Kakkunje", "pincode": "576222"}, {"place": "Kalathur South", "pincode": "574106"}, {"place": "Kallianapura", "pincode": "576114"}, {"place": "Kallya", "pincode": "574110"}, {"place": "Kalthod", "pincode": "576219"}, {"place": "Kamalashile", "pincode": "576229"}, {"place": "Kanajar", "pincode": "574102"}, {"place": "Kandlur", "pincode": "576211"}, {"place": "Kanthavara", "pincode": "574129"}, {"place": "Kanyana", "pincode": "576230"}, {"place": "Karje", "pincode": "576215"}, {"place": "Karkada", "pincode": "576225"}, {"place": "Karkala Bazar", "pincode": "574104"}, {"place": "Karkala", "pincode": "574104"}, {"place": "Karkala West", "pincode": "574104"}, {"place": "Karkunje", "pincode": "576283"}, {"place": "Katapadi", "pincode": "574105"}, {"place": "Kattebelthur", "pincode": "576230"}, {"place": "Kattingere", "pincode": "576120"}, {"place": "Kaup", "pincode": "574106"}, {"place": "Kavadi", "pincode": "576210"}, {"place": "Kavradi", "pincode": "576211"}, {"place": "Kedinje", "pincode": "574110"}, {"place": "Kedur", "pincode": "576231"}, {"place": "Kelarkalabettu", "pincode": "576105"}, {"place": "Kemmannu", "pincode": "576115"}, {"place": "Kemmundel", "pincode": "574119"}, {"place": "Kenchanur", "pincode": "576283"}, {"place": "Kenjur", "pincode": "576234"}, {"place": "Keradi", "pincode": "576233"}, {"place": "Kergal", "pincode": "576219"}, {"place": "Kervashe", "pincode": "574122"}, {"place": "Khambadakone", "pincode": "576219"}, {"place": "Kidiyur", "pincode": "576103"}, {"place": "Kirimanjeshwara", "pincode": "576219"}, {"place": "Koderi", "pincode": "576219"}, {"place": "Kodi", "pincode": "576217"}, {"place": "Kodi Kanyana", "pincode": "576226"}, {"place": "Kodibengre", "pincode": "576218"}, {"place": "Kodladi", "pincode": "576283"}, {"place": "Kodupanjimar", "pincode": "574116"}, {"place": "Kokkarne", "pincode": "576234"}, {"place": "Kolalagiri", "pincode": "576105"}, {"place": "Kollur", "pincode": "576220"}, {"place": "Koni", "pincode": "576217"}, {"place": "Korangrapadi", "pincode": "574118"}, {"place": "Korgi", "pincode": "576231"}, {"place": "Kota", "pincode": "576221"}, {"place": "Kotathattu", "pincode": "576221"}, {"place": "Koteshwara", "pincode": "576222"}, {"place": "Krodabailur", "pincode": "576227"}, {"place": "Krodashrama", "pincode": "576106"}, {"place": "Kuchur", "pincode": "576112"}, {"place": "Kudi", "pincode": "576113"}, {"place": "Kudrukere", "pincode": "576108"}, {"place": "Kukkehalli", "pincode": "576124"}, {"place": "Kukkikatte", "pincode": "576101"}, {"place": "Kukkuje", "pincode": "574108"}, {"place": "Kukkundur", "pincode": "576117"}, {"place": "Kukkundur West", "pincode": "576117"}, {"place": "Kulanje", "pincode": "576227"}, {"place": "Kumbhashi", "pincode": "576257"}, {"place": "Kumragodu", "pincode": "576213"}, {"place": "Kundabarandadi", "pincode": "576235"}, {"place": "Kundapura", "pincode": "576201"}, {"place": "Kundapura Market", "pincode": "576201"}, {"place": "Kunjal", "pincode": "576213"}, {"place": "Kunjarugiri", "pincode": "574105"}, {"place": "Kunjibettu", "pincode": "576102"}, {"place": "Kuntady", "pincode": "574244"}, {"place": "Kuthpadi", "pincode": "574118"}, {"place": "Kuthyar", "pincode": "574116"}, {"place": "Machattu", "pincode": "576227"}, {"place": "Madamakki", "pincode": "576212"}, {"place": "Majur", "pincode": "574106"}, {"place": "Mala", "pincode": "574122"}, {"place": "Mallar", "pincode": "574106"}, {"place": "Malpe", "pincode": "576108"}, {"place": "Manchikodi", "pincode": "576102"}, {"place": "Mandarthi", "pincode": "576223"}, {"place": "Manipal East", "pincode": "576104"}, {"place": "Manipal", "pincode": "576104"}, {"place": "Manipal Industrial Area", "pincode": "576104"}, {"place": "Manipura", "pincode": "576120"}, {"place": "Manipura West", "pincode": "574105"}, {"place": "Manjalthar", "pincode": "574122"}, {"place": "Manur", "pincode": "576221"}, {"place": "Maravanthe", "pincode": "576224"}, {"place": "Marne", "pincode": "576120"}, {"place": "Matapadi", "pincode": "576213"}, {"place": "Mattar", "pincode": "574116"}, {"place": "Mattu", "pincode": "574105"}, {"place": "Mayyadi", "pincode": "576214"}, {"place": "Melhosur", "pincode": "576233"}, {"place": "Mission Compound", "pincode": "576101"}, {"place": "Miyar", "pincode": "574107"}, {"place": "Molahalli", "pincode": "576222"}, {"place": "Moodubelle", "pincode": "576120"}, {"place": "Moodumata", "pincode": "576219"}, {"place": "Muddumane", "pincode": "576223"}, {"place": "Mudlakatte", "pincode": "576217"}, {"place": "Mudmunda", "pincode": "576233"}, {"place": "Mudradi", "pincode": "576112"}, {"place": "Mudur", "pincode": "576233"}, {"place": "Mundkur", "pincode": "576121"}, {"place": "Muniyal", "pincode": "574108"}, {"place": "Nada", "pincode": "576230"}, {"place": "Nadur", "pincode": "576223"}, {"place": "Nakre", "pincode": "576117"}, {"place": "Nalkur", "pincode": "576234"}, {"place": "Nallur", "pincode": "574122"}, {"place": "Nanchar", "pincode": "576234"}, {"place": "Nandalike", "pincode": "576111"}, {"place": "Nandikur", "pincode": "574111"}, {"place": "Navunda", "pincode": "576224"}, {"place": "Neelavara", "pincode": "576213"}, {"place": "Ninjoor", "pincode": "574244"}, {"place": "Nire", "pincode": "574102"}, {"place": "Nitte", "pincode": "574110"}, {"place": "Nittur", "pincode": "576103"}, {"place": "Nooralbettu", "pincode": "574107"}, {"place": "Nujadi", "pincode": "576233"}, {"place": "Padebettu", "pincode": "574111"}, {"place": "Padubelle", "pincode": "574116"}, {"place": "Padubidri", "pincode": "574111"}, {"place": "Padur", "pincode": "574106"}, {"place": "Paduvari", "pincode": "576214"}, {"place": "Paduyermal", "pincode": "574119"}, {"place": "Palimar", "pincode": "574112"}, {"place": "Palli", "pincode": "574244"}, {"place": "Panchanbettu", "pincode": "576113"}, {"place": "Pangala", "pincode": "576122"}, {"place": "Paniyur", "pincode": "574117"}, {"place": "Parampalli", "pincode": "576225"}, {"place": "Parappadi", "pincode": "574110"}, {"place": "Parkala", "pincode": "576107"}, {"place": "Patla", "pincode": "576107"}, {"place": "Perdur", "pincode": "576124"}, {"place": "Pernal", "pincode": "574116"}, {"place": "Pernankila", "pincode": "576113"}, {"place": "Pilar", "pincode": "574113"}, {"place": "Pithrodi", "pincode": "574118"}, {"place": "Puttur", "pincode": "576105"}, {"place": "Ragihaklu", "pincode": "576224"}, {"place": "Rattadi", "pincode": "576227"}, {"place": "Renjala", "pincode": "574114"}, {"place": "Sacherigudde", "pincode": "576121"}, {"place": "Saibarkatte", "pincode": "576210"}, {"place": "Saligrama", "pincode": "576225"}, {"place": "Salikeri", "pincode": "576213"}, {"place": "Salvadi", "pincode": "576222"}, {"place": "Santhekatte", "pincode": "576105"}, {"place": "Santhekatte-kalathur", "pincode": "576215"}, {"place": "Santhur", "pincode": "574111"}, {"place": "Sanur", "pincode": "574114"}, {"place": "Sasthan", "pincode": "576226"}, {"place": "Shankaranarayana", "pincode": "576227"}, {"place": "Shankarapura", "pincode": "574115"}, {"place": "Shedimane", "pincode": "576212"}, {"place": "Shenapura", "pincode": "576235"}, {"place": "Shiriyara", "pincode": "576210"}, {"place": "Shiroor", "pincode": "576124"}, {"place": "Shiruru", "pincode": "576228"}, {"place": "Shirva", "pincode": "574116"}, {"place": "Shivalli", "pincode": "576102"}, {"place": "Shivapura", "pincode": "576112"}, {"place": "Siddapura", "pincode": "576229"}, {"place": "Sitanadi", "pincode": "576112"}, {"place": "Someshwara", "pincode": "576112"}, {"place": "Sooda", "pincode": "574116"}, {"place": "Souda", "pincode": "576222"}, {"place": "Subhash Nagar", "pincode": "574105"}, {"place": "Taggarshe", "pincode": "576214"}, {"place": "Tallur", "pincode": "576230"}, {"place": "Tarapathi", "pincode": "576232"}, {"place": "Tekkatte", "pincode": "576231"}, {"place": "Tellar", "pincode": "576117"}, {"place": "Tenkabettu", "pincode": "576105"}, {"place": "Tenkanidiyur", "pincode": "576106"}, {"place": "Thottam", "pincode": "576108"}, {"place": "Trasi", "pincode": "576235"}, {"place": "Uchila", "pincode": "574117"}, {"place": "Udupi Courts", "pincode": "576101"}, {"place": "Udupi", "pincode": "576101"}, {"place": "Udyavara", "pincode": "574118"}, {"place": "Uliyaragoli", "pincode": "574106"}, {"place": "Ullur", "pincode": "576229"}, {"place": "Ultoor", "pincode": "576231"}, {"place": "Uppinakudru", "pincode": "576230"}, {"place": "Uppunda", "pincode": "576232"}, {"place": "Uppur", "pincode": "576105"}, {"place": "Vakwadi", "pincode": "576257"}, {"place": "Vandar", "pincode": "576223"}, {"place": "Vandse", "pincode": "576233"}, {"place": "Vanjarakatte", "pincode": "574129"}, {"place": "Varanga", "pincode": "574108"}, {"place": "Vishwasnagar", "pincode": "574108"}, {"place": "Yadyadi-mathyadi", "pincode": "576222"}, {"place": "Yedabettu", "pincode": "576226"}, {"place": "Yedamoge", "pincode": "576282"}, {"place": "Yedthadi", "pincode": "576210"}, {"place": "Yedthare", "pincode": "576214"}, {"place": "Yelajith", "pincode": "576214"}, {"place": "Yellur", "pincode": "574113"}, {"place": "Yennehole", "pincode": "574101"}, {"place": "Yerlapady", "pincode": "574102"}, {"place": "Yermal", "pincode": "574119"}]