[{"place": "Post office", "pincode": "Pincode"}, {"place": "Abar", "pincode": "323024"}, {"place": "Ajanda", "pincode": "323603"}, {"place": "Ajeta", "pincode": "323803"}, {"place": "Akoda B.O", "pincode": "323001"}, {"place": "Alod", "pincode": "323024"}, {"place": "Alphanagar", "pincode": "323021"}, {"place": "Amli", "pincode": "323022"}, {"place": "Anghora", "pincode": "323614"}, {"place": "Antarda", "pincode": "323616"}, {"place": "Anthada", "pincode": "323021"}, {"place": "Arnetha", "pincode": "323301"}, {"place": "Babai", "pincode": "323613"}, {"place": "Bachola", "pincode": "323801"}, {"place": "Bada Kheda", "pincode": "323603"}, {"place": "Badodiya B.O", "pincode": "323001"}, {"place": "Bajar", "pincode": "323021"}, {"place": "Balapura", "pincode": "323801"}, {"place": "Balban", "pincode": "323614"}, {"place": "Balchand Para Bundi", "pincode": "323001"}, {"place": "Balkasa", "pincode": "323301"}, {"place": "Ballop", "pincode": "323021"}, {"place": "Bamangaon", "pincode": "323801"}, {"place": "Bamori", "pincode": "323803"}, {"place": "Bansi", "pincode": "323802"}, {"place": "Baranaya Gaon", "pincode": "323024"}, {"place": "Barundhan", "pincode": "323021"}, {"place": "Basni", "pincode": "323025"}, {"place": "Basoli", "pincode": "323024"}, {"place": "Baswada", "pincode": "323603"}, {"place": "Bhajneri", "pincode": "323802"}, {"place": "Bhawanipura", "pincode": "323024"}, {"place": "Bherupura Antri B.O", "pincode": "323001"}, {"place": "Bherupura Ojhha", "pincode": "323803"}, {"place": "Bhiya", "pincode": "323602"}, {"place": "Borda B.O", "pincode": "323001"}, {"place": "Borda Kachhiyan", "pincode": "323803"}, {"place": "Borkhandi B.O", "pincode": "323001"}, {"place": "Budhpura", "pincode": "323022"}, {"place": "Bundi", "pincode": "323001"}, {"place": "Chainpuria", "pincode": "323801"}, {"place": "Chanda Khurd", "pincode": "323614"}, {"place": "Chardana", "pincode": "323301"}, {"place": "Chatarganj", "pincode": "323023"}, {"place": "Chatarpura B.O", "pincode": "323001"}, {"place": "Chetan", "pincode": "323024"}, {"place": "Chitawa", "pincode": "323602"}, {"place": "Dabeta", "pincode": "323802"}, {"place": "Dabi", "pincode": "323022"}, {"place": "Dablana", "pincode": "323024"}, {"place": "Daulatpura", "pincode": "323614"}, {"place": "Dehit", "pincode": "323021"}, {"place": "Dei Kheda", "pincode": "323603"}, {"place": "Dei", "pincode": "323802"}, {"place": "Dhagaria", "pincode": "323603"}, {"place": "Dhanesar", "pincode": "323022"}, {"place": "Dhanugaon", "pincode": "323801"}, {"place": "Dhowara", "pincode": "323024"}, {"place": "Dokun", "pincode": "323802"}, {"place": "Dolara B.O", "pincode": "323001"}, {"place": "Dora", "pincode": "323021"}, {"place": "Dugari", "pincode": "323802"}, {"place": "Gadarda", "pincode": "323022"}, {"place": "Gamach", "pincode": "323602"}, {"place": "Gambhira", "pincode": "323801"}, {"place": "Gendoli", "pincode": "323803"}, {"place": "Ghat Ka Barana", "pincode": "323603"}, {"place": "Gothra", "pincode": "323024"}, {"place": "Guda Deo Ji", "pincode": "323802"}, {"place": "Guda Gokulpura", "pincode": "323025"}, {"place": "Guda Turkadi", "pincode": "323024"}, {"place": "Gudasadawartia", "pincode": "323802"}, {"place": "Gudha Nathawatan B.O", "pincode": "323001"}, {"place": "Gumanpura", "pincode": "323021"}, {"place": "Hindoli", "pincode": "323023"}, {"place": "Hingonia", "pincode": "323301"}, {"place": "Indergarh", "pincode": "323613"}, {"place": "Jaithal", "pincode": "323301"}, {"place": "Jajawar", "pincode": "323801"}, {"place": "Jaloda", "pincode": "323301"}, {"place": "Jamitpura", "pincode": "323021"}, {"place": "Jarkhoda", "pincode": "323802"}, {"place": "Jawharsagar Dam", "pincode": "323302"}, {"place": "Jetpur", "pincode": "323803"}, {"place": "Jhakhmund", "pincode": "323021"}, {"place": "Jhali Ji Ka Barana", "pincode": "323803"}, {"place": "Kachola", "pincode": "323025"}, {"place": "Kaithuda", "pincode": "323616"}, {"place": "Kalpuria", "pincode": "323022"}, {"place": "Kapren", "pincode": "323301"}, {"place": "Karwala", "pincode": "323602"}, {"place": "Karwala Ki Jhopri", "pincode": "323301"}, {"place": "Karwar", "pincode": "323616"}, {"place": "Kesoraipatan", "pincode": "323601"}, {"place": "Kesoraipatan Sugar Factoy", "pincode": "323602"}, {"place": "Khadipur", "pincode": "323022"}, {"place": "Khajoori", "pincode": "323616"}, {"place": "Khanpura", "pincode": "323801"}, {"place": "Khatkar", "pincode": "323803"}, {"place": "Khiniya B.O", "pincode": "323001"}, {"place": "Khyawda", "pincode": "323803"}, {"place": "Laban", "pincode": "323603"}, {"place": "Ladpura", "pincode": "323021"}, {"place": "Lakheri Gaon", "pincode": "323615"}, {"place": "Lakheri", "pincode": "323603"}, {"place": "Lalpura B.O", "pincode": "323001"}, {"place": "Lambakho", "pincode": "323022"}, {"place": "Laxmipura", "pincode": "323021"}, {"place": "Leeleda", "pincode": "323021"}, {"place": "Lesarda", "pincode": "323602"}, {"place": "Loicha", "pincode": "323022"}, {"place": "Luharpura", "pincode": "323803"}, {"place": "Maiza", "pincode": "323602"}, {"place": "Makhida", "pincode": "323603"}, {"place": "Mangal B.O", "pincode": "323001"}, {"place": "Mani", "pincode": "323616"}, {"place": "Matunda B.O", "pincode": "323001"}, {"place": "Mendi", "pincode": "323024"}, {"place": "Mohanpura", "pincode": "323613"}, {"place": "Morsan", "pincode": "323802"}, {"place": "Nainwan", "pincode": "323801"}, {"place": "Namana", "pincode": "323022"}, {"place": "Nawalpura", "pincode": "323614"}, {"place": "Nayagaon", "pincode": "323803"}, {"place": "Neem Ka Kheda B.O", "pincode": "323001"}, {"place": "Neem Ka Khera", "pincode": "323616"}, {"place": "Negharh", "pincode": "323024"}, {"place": "New Colony Bundi", "pincode": "323001"}, {"place": "Notada", "pincode": "323603"}, {"place": "Notada", "pincode": "323021"}, {"place": "Owan", "pincode": "323024"}, {"place": "Pagaran", "pincode": "323025"}, {"place": "Papdi", "pincode": "323603"}, {"place": "Pech Ki Baori", "pincode": "323025"}, {"place": "Peepliya", "pincode": "323803"}, {"place": "Phalenda", "pincode": "323025"}, {"place": "Pholai", "pincode": "323803"}, {"place": "Phuleta", "pincode": "323801"}, {"place": "Radi", "pincode": "323602"}, {"place": "Raithal", "pincode": "323803"}, {"place": "Rajalawata", "pincode": "323801"}, {"place": "Rajwas", "pincode": "323803"}, {"place": "Ramchandra Ji Ka Kheda", "pincode": "323024"}, {"place": "Ramganj B.O", "pincode": "323001"}, {"place": "Ramnagar B.O", "pincode": "323001"}, {"place": "Ranipura", "pincode": "323024"}, {"place": "Rebarpura", "pincode": "323603"}, {"place": "Rehana", "pincode": "323803"}, {"place": "Renthoda", "pincode": "323616"}, {"place": "Ronija", "pincode": "323024"}, {"place": "Roteda", "pincode": "323301"}, {"place": "Sadera", "pincode": "323802"}, {"place": "Sahan", "pincode": "323802"}, {"place": "Sahaspuriya", "pincode": "323023"}, {"place": "Sakhawda", "pincode": "323603"}, {"place": "Samidhi", "pincode": "323801"}, {"place": "Sanwatgarh", "pincode": "323024"}, {"place": "Sarsala", "pincode": "323602"}, {"place": "Sathur", "pincode": "323024"}, {"place": "Silore B.O", "pincode": "323001"}, {"place": "Sisola", "pincode": "323801"}, {"place": "Songar", "pincode": "323602"}, {"place": "Soran", "pincode": "323024"}, {"place": "Sumerganj Mandi", "pincode": "323614"}, {"place": "Sunwasa", "pincode": "323021"}, {"place": "Suwania", "pincode": "323801"}, {"place": "Talab Gaon B.O", "pincode": "323001"}, {"place": "Talera", "pincode": "323021"}, {"place": "Talwas", "pincode": "323616"}, {"place": "Thana", "pincode": "323025"}, {"place": "Thikarda B.O", "pincode": "323001"}, {"place": "Tirath", "pincode": "323602"}, {"place": "Tonkra", "pincode": "323025"}, {"place": "Umar", "pincode": "323025"}, {"place": "Utharana", "pincode": "323603"}, {"place": "Vijaygarh", "pincode": "323025"}]